DAY_16/FSM/MOORE MODEL/moore_overlapping.v
module moore_1011_overlap (
input clk,
input rst,
input x,
output reg z
);
reg [2:0] state, next_state;
parameter S0 = 3'b000,
          S1 = 3'b001,
          S2 = 3'b010,
          S3 = 3'b011,
          S4 = 3'b100;  
always @(*) begin
    case (state)
        S0: next_state = x ? S1 : S0;
        S1: next_state = x ? S1 : S2;
        S2: next_state = x ? S3 : S0;
        S3: next_state = x ? S4 : S2;
        S4: next_state = x ? S1 : S2; 
        default: next_state = S0;
    endcase
end
always @(posedge clk or posedge rst) begin
    if (rst)
        state <= S0;
    else
        state <= next_state;
end
always @(*) begin
    if (state == S4)
        z = 1;
    else
        z = 0;
end
endmodule


//OUTPUT//
T=0 x=0 z=0
T=20 x=1 z=0
T=30 x=0 z=0
T=40 x=1 z=0
T=55 x=1 z=1
T=60 x=0 z=1
T=65 x=0 z=0
T=70 x=1 z=0
T=85 x=1 z=1
T=95 x=1 z=0

DAY_16/FSM/MOORE MODEL/moore_overlapping_tb.v
module tb_moore_1011_overlap;
reg clk;
reg rst;
reg x;
wire z;
moore_1011_overlap DUT (
.clk(clk),
.rst(rst),
.x(x),
.z(z)
);
always #5 clk = ~clk;
initial begin
    clk = 0;
    rst = 1;
    x = 0;
    #10 rst = 0;
  
    #10 x = 1;
    #10 x = 0;
    #10 x = 1;
    #10 x = 1;   

    #10 x = 0;
    #10 x = 1;
    #10 x = 1;   
    #30 $finish;
end
initial begin
    $dumpfile("moore_1011_overlap.vcd");
    $dumpvars(0, tb_moore_1011_overlap);
    $monitor("T=%0t x=%b z=%b", $time, x, z);
end
endmodule

DAY_16/FSM/MOORE MODEL/moore_1011_overlap.vcd
$date
	Tue Dec 30 10:40:17 2025
$end
$version
	Icarus Verilog
$end
$timescale
	1s
$end
$scope module tb_moore_1011_overlap $end
$var wire 1 ! z $end
$var reg 1 " clk $end
$var reg 1 # rst $end
$var reg 1 $ x $end
$scope module DUT $end
$var wire 1 " clk $end
$var wire 1 # rst $end
$var wire 1 $ x $end
$var parameter 3 % S0 $end
$var parameter 3 & S1 $end
$var parameter 3 ' S2 $end
$var parameter 3 ( S3 $end
$var parameter 3 ) S4 $end
$var reg 3 * next_state [2:0] $end
$var reg 3 + state [2:0] $end
$var reg 1 ! z $end
$upscope $end
$upscope $end
$enddefinitions $end
$comment Show the parameter values. $end
$dumpall
b100 )
b11 (
b10 '
b1 &
b0 %
$end
#0
$dumpvars
b0 +
b0 *
0$
1#
0"
0!
$end
#5
1"
#10
0"
0#
#15
1"
#20
b1 *
0"
1$
#25
b1 +
1"
#30
b10 *
0"
0$
#35
b0 *
b10 +
1"
#40
b11 *
0"
1$
#45
b100 *
b11 +
1"
#50
0"
#55
1!
b1 *
b100 +
1"
#60
b10 *
0"
0$
#65
0!
b0 *
b10 +
1"
#70
b11 *
0"
1$
#75
b100 *
b11 +
1"
#80
0"
#85
1!
b1 *
b100 +
1"
#90
0"
#95
0!
b1 +
1"
